{"stats":{"minecraft:used":{"culturaldelights:fish_taco":5,"minecraft:iron_shovel":483,"minecraft:oak_sign":6,"minecraft:diamond_hoe":224,"minecraft:poppy":6,"culturaldelights:pork_wrap":5,"minecraft:chest":18,"minecraft:iron_sword":120,"minecraft:nether_wart":10,"minecraft:soul_sand":21,"minecraft:carrot":4,"minecraft:deepslate_tile_slab":2,"farmersdelight:steak_and_potatoes":5,"minecraft:tuff":6,"minecraft:music_disc_13":1,"farmersdelight:roast_chicken":5,"minecraft:glass":139,"culturaldelights:mutton_sandwich":7,"minecraft:dark_oak_button":1,"farmersdelight:bacon_sandwich":5,"minecraft:bow":14,"minecraft:furnace":16,"minecraft:oak_sapling":30,"minecraft:egg":1,"farmersdelight:salmon_roll":5,"minecraft:diorite":1,"minecraft:warped_fungus_on_a_stick":11,"culturaldelights:chicken_roll_slice":5,"minecraft:stone_pickaxe":127,"minecraft:oak_planks":293,"minecraft:wooden_pickaxe":7,"minecraft:diamond_axe":788,"culturaldelights:midori_roll_slice":13,"minecraft:white_wool":690,"minecraft:sand":1,"farmersdelight:chicken_sandwich":5,"farmersdelight:cod_roll":5,"farmersdelight:pasta_with_mutton_chop":9,"farmersdelight:stuffed_pumpkin":5,"minecraft:shears":387,"culturaldelights:fried_eggplant_pasta":5,"culturaldelights:chicken_taco":5,"minecraft:cobbled_deepslate_stairs":43,"minecraft:string":1,"minecraft:lectern":1,"minecraft:oak_pressure_plate":9,"minecraft:gravel":48,"minecraft:diamond_sword":919,"minecraft:grindstone":1,"minecraft:andesite":26,"minecraft:oak_boat":11,"sebsfoodcore:shrimp_roll":2,"minecraft:oak_fence":60,"farmersdelight:kelp_roll_slice":5,"minecraft:rose_bush":4,"minecraft:white_tulip":1,"farmersdelight:vegetable_noodles":5,"minecraft:stone_shovel":31,"minecraft:netherrack":236,"minecraft:oak_door":6,"minecraft:torch":998,"minecraft:brewing_stand":1,"minecraft:dirt":55,"minecraft:granite":2,"minecraft:iron_hoe":250,"minecraft:iron_axe":34,"minecraft:oak_stairs":14,"minecraft:spruce_button":1,"minecraft:goat_horn":4,"minecraft:deepslate_tile_stairs":55,"farmersdelight:squid_ink_pasta":1,"minecraft:cobbled_deepslate":1733,"farmersdelight:shepherds_pie":1,"farmersdelight:mutton_wrap":5,"minecraft:water_bucket":429,"minecraft:cobblestone_stairs":123,"minecraft:birch_boat":9,"minecraft:vine":1,"minecraft:rail":3,"minecraft:music_disc_cat":4,"minecraft:crafting_table":27,"minecraft:book":1,"farmersdelight:bacon_and_eggs":6,"minecraft:oak_log":382,"minecraft:diamond_pickaxe":14151,"farmersdelight:pasta_with_meatballs":9,"minecraft:iron_pickaxe":2264,"minecraft:map":1,"minecraft:cobblestone":1662,"farmersdelight:egg_sandwich":9,"minecraft:bucket":431,"alexsmobs:animal_dictionary":3,"minecraft:jukebox":1},"minecraft:picked_up":{"minecraft:lead":11,"minecraft:diamond_sword":1,"minecraft:stone_slab":5,"minecraft:brewing_stand":1,"minecraft:amethyst_block":370,"minecraft:music_disc_cat":4,"minecraft:string":19,"minecraft:raw_copper":15,"minecraft:gold_nugget":31,"minecraft:cobbled_deepslate":9460,"minecraft:smooth_stone":8,"minecraft:spruce_planks":1,"minecraft:white_tulip":1,"minecraft:rose_bush":4,"minecraft:calcite":27,"minecraft:melon_slice":4,"minecraft:furnace":4,"minecraft:stick":44,"minecraft:oak_fence":13,"minecraft:torch":189,"minecraft:golden_axe":1,"minecraft:diorite":109,"minecraft:vine":1,"minecraft:deepslate_tile_stairs":28,"minecraft:stone_sword":1,"minecraft:blaze_rod":1,"minecraft:obsidian":3,"minecraft:cobblestone":3100,"minecraft:andesite":143,"alexsmobs:bear_fur":2,"minecraft:flint":63,"minecraft:tuff":723,"minecraft:lapis_lazuli":556,"minecraft:dirt":257,"minecraft:twisting_vines":6,"minecraft:bone":40,"minecraft:glass":96,"minecraft:wheat_seeds":50,"minecraft:raw_gold":139,"minecraft:oak_planks":19,"minecraft:music_disc_13":2,"minecraft:warped_wart_block":7,"minecraft:sand":75,"alexsmobs:animal_dictionary":1,"minecraft:mossy_cobblestone":10,"minecraft:diamond":186,"minecraft:crossbow":9,"minecraft:granite":146,"minecraft:spruce_button":1,"minecraft:emerald":6,"alexsmobs:maggot":3,"minecraft:oak_sapling":36,"minecraft:netherrack":452,"minecraft:dark_oak_fence":1,"minecraft:crafting_table":6,"minecraft:nether_wart":10,"minecraft:brown_mushroom":4,"minecraft:blue_orchid":4,"minecraft:beef":20,"minecraft:oak_boat":10,"minecraft:poppy":6,"minecraft:lectern":1,"minecraft:chest":1,"minecraft:egg":2,"minecraft:raw_iron":273,"minecraft:stone":15,"minecraft:bowl":1,"minecraft:redstone":1010,"minecraft:dark_oak_planks":1,"minecraft:mutton":2,"minecraft:white_wool":485,"minecraft:rail":5,"minecraft:cracked_deepslate_tiles":1,"minecraft:leather":13,"minecraft:oak_log":632,"minecraft:cobbled_deepslate_stairs":3,"minecraft:gunpowder":5,"minecraft:cobblestone_stairs":7,"minecraft:deepslate_tile_slab":2,"minecraft:white_banner":10,"minecraft:smooth_sandstone":1,"minecraft:kelp":2,"minecraft:apple":7,"minecraft:warped_stem":8,"minecraft:soul_sand":21,"minecraft:iron_sword":1,"minecraft:warped_fungus":27,"minecraft:smooth_basalt":31,"minecraft:birch_boat":8,"minecraft:quartz":4,"minecraft:dandelion":22,"minecraft:raw_iron_block":1,"minecraft:gravel":518,"minecraft:amethyst_shard":152,"minecraft:spider_eye":6,"minecraft:slime_ball":4,"minecraft:warped_roots":8,"minecraft:coal":405},"minecraft:killed":{"minecraft:cave_spider":1,"minecraft:spider":31,"minecraft:piglin":3,"alexsmobs:grizzly_bear":2,"minecraft:creeper":7,"minecraft:pillager":99,"minecraft:goat":1,"alexsmobs:fly":2,"alexsmobs:komodo_dragon":1,"minecraft:blaze":3,"minecraft:cow":10,"minecraft:slime":4,"sebsarchaeology:goblin_warrior":94,"alexsmobs:gazelle":1,"minecraft:wither_skeleton":8},"minecraft:dropped":{"minecraft:iron_sword":2,"minecraft:birch_planks":4,"minecraft:lapis_lazuli":110,"minecraft:oak_log":13,"minecraft:diamond":2,"minecraft:crossbow":9,"minecraft:warped_roots":8,"minecraft:leather":13,"minecraft:music_disc_13":2,"minecraft:flint":9,"minecraft:dark_oak_fence":1,"minecraft:mutton":2,"minecraft:amethyst_shard":28,"minecraft:iron_pickaxe":1,"minecraft:white_wool":1,"minecraft:bone":11,"minecraft:gravel":29,"sebsarchaeology:travelers_compass":2,"minecraft:twisting_vines":6,"minecraft:cobbled_deepslate":194,"alexsmobs:animal_dictionary":2,"minecraft:obsidian":3,"minecraft:oak_planks":9,"minecraft:beef":20,"minecraft:quartz":4,"minecraft:egg":1,"minecraft:wheat_seeds":49,"minecraft:golden_axe":2,"minecraft:iron_helmet":1,"minecraft:cobblestone":75,"minecraft:lead":1,"minecraft:book":4,"minecraft:granite":1,"minecraft:spruce_button":1,"minecraft:stick":25,"minecraft:iron_leggings":1,"minecraft:smooth_stone":8,"minecraft:paper":15,"minecraft:string":4,"minecraft:smooth_sandstone":1,"minecraft:dandelion":22,"minecraft:smooth_basalt":2,"minecraft:redstone":334,"minecraft:kelp":2,"alexsmobs:maggot":1,"minecraft:stone_sword":1,"minecraft:bowl":9,"minecraft:iron_boots":1,"minecraft:stone_slab":5,"minecraft:filled_map":2,"minecraft:diamond_sword":1,"minecraft:stone":15,"minecraft:iron_chestplate":1,"minecraft:oak_sapling":4,"minecraft:wooden_shovel":1,"minecraft:spider_eye":1,"minecraft:blue_orchid":4,"minecraft:stone_pickaxe":2,"minecraft:wooden_pickaxe":1,"minecraft:calcite":5},"minecraft:broken":{"minecraft:iron_shovel":1,"minecraft:shears":1,"minecraft:iron_hoe":1,"sebsarchaeology:travelers_compass":2,"minecraft:iron_pickaxe":8},"minecraft:custom":{"minecraft:interact_with_crafting_table":111,"minecraft:open_barrel":114,"minecraft:leave_game":8,"minecraft:time_since_death":1329455,"minecraft:sprint_one_cm":6567299,"minecraft:drop":185,"minecraft:talked_to_villager":5,"minecraft:play_time":1329455,"minecraft:jump":11566,"minecraft:walk_on_water_one_cm":170915,"minecraft:enchant_item":16,"minecraft:interact_with_furnace":74,"minecraft:play_record":5,"minecraft:interact_with_cartography_table":1,"minecraft:sleep_in_bed":17,"minecraft:damage_dealt":52288,"minecraft:crouch_one_cm":143939,"minecraft:interact_with_smoker":2,"minecraft:mob_kills":282,"minecraft:interact_with_anvil":3,"minecraft:climb_one_cm":32467,"minecraft:walk_one_cm":3936506,"minecraft:strider_one_cm":468,"minecraft:sneak_time":38846,"minecraft:walk_under_water_one_cm":29524,"minecraft:boat_one_cm":1798605,"minecraft:interact_with_blast_furnace":1,"minecraft:total_world_time":1329455,"minecraft:interact_with_grindstone":17,"minecraft:interact_with_stonecutter":3,"minecraft:time_since_rest":50838,"minecraft:damage_taken":8752,"minecraft:trigger_trapped_chest":9,"minecraft:swim_one_cm":35558,"minecraft:fly_one_cm":1709933,"minecraft:open_chest":858,"minecraft:fall_one_cm":261557},"minecraft:mined":{"minecraft:large_amethyst_bud":2,"minecraft:cobbled_deepslate_stairs":3,"minecraft:cobblestone_stairs":7,"minecraft:sculk_vein":10,"minecraft:brewing_stand":1,"minecraft:obsidian":3,"minecraft:cave_vines_plant":1,"minecraft:granite":146,"minecraft:budding_amethyst":43,"minecraft:grass_block":155,"minecraft:deepslate_tile_stairs":28,"minecraft:nether_wart":10,"minecraft:spawner":4,"minecraft:smooth_stone":8,"minecraft:raw_iron_block":1,"minecraft:iron_ore":148,"minecraft:cobbled_deepslate":110,"minecraft:deepslate_lapis_ore":52,"minecraft:twisting_vines":3,"minecraft:sculk_shrieker":1,"minecraft:small_amethyst_bud":4,"minecraft:blue_orchid":2,"minecraft:deepslate_redstone_ore":201,"minecraft:twisting_vines_plant":3,"minecraft:medium_amethyst_bud":1,"minecraft:amethyst_cluster":29,"minecraft:deepslate_tile_slab":2,"minecraft:torch":82,"minecraft:calcite":28,"minecraft:poppy":6,"minecraft:melon":1,"minecraft:chest":1,"minecraft:dead_bush":1,"minecraft:mushroom_stem":3,"minecraft:glass":2,"minecraft:nether_quartz_ore":4,"minecraft:cobblestone":126,"minecraft:oak_planks":18,"minecraft:wall_torch":88,"minecraft:amethyst_block":371,"minecraft:warped_nylium":16,"minecraft:warped_fungus":26,"minecraft:grass":93,"minecraft:cracked_deepslate_tiles":1,"minecraft:oak_log":641,"minecraft:sand":76,"minecraft:dirt":102,"minecraft:smooth_basalt":34,"minecraft:netherrack":455,"minecraft:oak_leaves":207,"minecraft:deepslate":9471,"minecraft:nether_gold_ore":8,"minecraft:tuff":794,"minecraft:mossy_cobblestone":10,"minecraft:deepslate_diamond_ore":106,"minecraft:dark_oak_fence":3,"minecraft:brown_mushroom_block":27,"minecraft:kelp":1,"minecraft:large_fern":6,"minecraft:furnace":4,"minecraft:andesite":143,"minecraft:deepslate_iron_ore":86,"minecraft:vine":1,"minecraft:rail":2,"minecraft:warped_stem":8,"minecraft:stone":3089,"minecraft:white_tulip":1,"minecraft:white_wool":483,"minecraft:soul_sand":21,"minecraft:dandelion":2,"minecraft:oak_fence":16,"minecraft:smooth_sandstone":1,"minecraft:crafting_table":6,"minecraft:emerald_ore":6,"minecraft:warped_roots":3,"minecraft:rose_bush":4,"minecraft:lectern":1,"minecraft:tall_grass":3,"minecraft:copper_ore":5,"minecraft:lapis_ore":11,"minecraft:deepslate_gold_ore":91,"minecraft:sculk":568,"minecraft:diorite":109,"minecraft:warped_wart_block":7,"minecraft:coal_ore":361,"minecraft:gravel":313,"minecraft:cobweb":57,"minecraft:gold_ore":4,"minecraft:fern":12},"minecraft:crafted":{"minecraft:grindstone":1,"minecraft:oak_planks":892,"minecraft:oak_sign":6,"minecraft:oak_pressure_plate":9,"minecraft:birch_boat":1,"minecraft:stone":18,"minecraft:cobblestone_stairs":116,"minecraft:diamond_shovel":1,"minecraft:glass":128,"minecraft:diamond_helmet":2,"minecraft:bow":2,"minecraft:diamond_leggings":2,"minecraft:iron_boots":1,"minecraft:chest":17,"minecraft:oak_fence":72,"minecraft:deepslate":9,"minecraft:wooden_shovel":1,"minecraft:arrow":168,"minecraft:diamond_axe":1,"minecraft:crafting_table":21,"minecraft:wooden_pickaxe":1,"minecraft:iron_helmet":1,"minecraft:birch_planks":4,"minecraft:iron_chestplate":1,"minecraft:diamond_pickaxe":6,"minecraft:stick":360,"minecraft:stone_slab":6,"minecraft:iron_ingot":104,"minecraft:iron_pickaxe":10,"minecraft:shears":2,"minecraft:oak_door":9,"minecraft:raw_iron":9,"minecraft:stone_shovel":1,"minecraft:fishing_rod":3,"minecraft:jukebox":1,"minecraft:diamond_hoe":1,"minecraft:spruce_button":1,"minecraft:furnace":15,"minecraft:bone_meal":30,"minecraft:iron_axe":1,"minecraft:iron_hoe":1,"minecraft:stone_pickaxe":2,"minecraft:diamond_boots":2,"minecraft:cobbled_deepslate_stairs":40,"minecraft:redstone_block":61,"minecraft:lead":8,"minecraft:diamond_sword":1,"minecraft:iron_sword":1,"minecraft:bucket":3,"minecraft:dark_oak_button":1,"minecraft:air":0,"minecraft:oak_boat":1,"minecraft:warped_fungus_on_a_stick":3,"minecraft:oak_stairs":40,"minecraft:iron_shovel":2,"minecraft:deepslate_tile_stairs":5,"minecraft:iron_leggings":1,"minecraft:torch":816,"minecraft:lapis_block":44,"minecraft:diamond_chestplate":2}},"DataVersion":3465}